algortest/__init__.py
algortest/core.py
algortest/test.py
algortest-2.dist-info/METADATA
algortest-2.dist-info/WHEEL
algortest-2.dist-info/top_level.txt
algortest-2.dist-info/RECORD
